{
  "asof_ts": 1774533124,
  "fetch_latency_seconds": 1.029453992843628,
  "tickers": {
    "VOO": {
      "price": 602.74,
      "change_pct": -0.4821186804477693
    },
    "SPY": {
      "price": 653.55,
      "change_pct": -0.49785329313968746
    },
    "NVDA": {
      "price": 175.61,
      "change_pct": -1.7181553615401797
    },
    "MSFT": {
      "price": 372.81,
      "change_pct": 0.47703751617075835
    },
    "AAPL": {
      "price": 252.37,
      "change_pct": -0.09896286913150187
    },
    "GOOGL": {
      "price": 286.37,
      "change_pct": -1.5673873440346482
    },
    "AMZN": {
      "price": 209.47,
      "change_pct": -1.0580511076472576
    },
    "TSLA": {
      "price": 383.32,
      "change_pct": -0.6814354190957366
    },
    "META": {
      "price": 577.86,
      "change_pct": -2.862714115214573
    },
    "BRK-B": {
      "price": 476.56,
      "change_pct": 0.07770007770007865
    },
    "BLK": {
      "price": 984.69,
      "change_pct": 0.34034748051154345
    }
  },
  "generated_at": 1774533125
}