{
  "asof_ts": 1772636448,
  "fetch_latency_seconds": 12.442988157272339,
  "tickers": {
    "SPY": {
      "price": 682.01,
      "change_pct": 0.2469389854923272
    },
    "NVDA": {
      "price": 181.08,
      "change_pct": 0.5720633157456267
    },
    "MSFT": {
      "price": 405.89,
      "change_pct": 0.48523258980515915
    },
    "AAPL": {
      "price": 262.66,
      "change_pct": -0.4132701421800853
    },
    "GOOGL": {
      "price": 303.24,
      "change_pct": -0.11199683773633803
    },
    "AMZN": {
      "price": 214.86,
      "change_pct": 2.936808316964511
    },
    "TSLA": {
      "price": 398.37,
      "change_pct": 1.5136457457380927
    },
    "META": {
      "price": 666.99,
      "change_pct": 1.818098552848502
    },
    "BRK-B": {
      "price": 484.25,
      "change_pct": 0.6003822502908398
    },
    "BLK": {
      "price": 1049.97,
      "change_pct": -0.24890983193835123
    }
  },
  "generated_at": 1772636461
}