{
  "asof_ts": 1772463375,
  "fetch_latency_seconds": 1.840273141860962,
  "tickers": {
    "VOO": {
      "price": 627.73,
      "change_pct": -0.5245309330628717
    },
    "SPY": {
      "price": 682.5,
      "change_pct": -0.5087537719208748
    },
    "NVDA": {
      "price": 179.51,
      "change_pct": 1.3093289689034333
    },
    "MSFT": {
      "price": 395.94,
      "change_pct": 0.8147884096348701
    },
    "AAPL": {
      "price": 262.63,
      "change_pct": -0.5867211749564734
    },
    "GOOGL": {
      "price": 304.69,
      "change_pct": -2.2677700795483684
    },
    "AMZN": {
      "price": 206.97,
      "change_pct": -1.4428571428571435
    },
    "TSLA": {
      "price": 395.85,
      "change_pct": -1.6546172765893936
    },
    "META": {
      "price": 646.52,
      "change_pct": -0.25610170014501654
    },
    "BRK-B": {
      "price": 486.52,
      "change_pct": -3.6498663233983577
    },
    "BLK": {
      "price": 1055.37,
      "change_pct": -0.739256792979894
    }
  },
  "generated_at": 1772463377
}