{
  "asof_ts": 1772813060,
  "fetch_latency_seconds": 0.8156743049621582,
  "tickers": {
    "VOO": {
      "price": 621.41,
      "change_pct": -0.8615050812845964
    },
    "SPY": {
      "price": 675.69,
      "change_pct": -0.8248814783284982
    },
    "NVDA": {
      "price": 181.96,
      "change_pct": -0.7526999018217495
    },
    "MSFT": {
      "price": 412.53,
      "change_pct": 0.4504723872601456
    },
    "AAPL": {
      "price": 257.87,
      "change_pct": -0.9297322217526666
    },
    "GOOGL": {
      "price": 300.18,
      "change_pct": -0.23265089072054929
    },
    "AMZN": {
      "price": 216.49,
      "change_pct": -1.1190280442130214
    },
    "TSLA": {
      "price": 398.66,
      "change_pct": -1.6989273825668811
    },
    "META": {
      "price": 648.89,
      "change_pct": -1.76816991386228
    },
    "BRK-B": {
      "price": 493.77,
      "change_pct": -1.3249400479616298
    },
    "BLK": {
      "price": 976.44,
      "change_pct": -5.657971014492748
    }
  },
  "generated_at": 1772813061
}