{
  "asof_ts": 1773862324,
  "fetch_latency_seconds": 1.514702558517456,
  "tickers": {
    "VOO": {
      "price": 609.76,
      "change_pct": -1.1557976300474957
    },
    "SPY": {
      "price": 662.96,
      "change_pct": -1.1672803709059358
    },
    "NVDA": {
      "price": 181.36,
      "change_pct": -0.31330731600065587
    },
    "MSFT": {
      "price": 392.23,
      "change_pct": -1.7976515360156247
    },
    "AAPL": {
      "price": 249.83,
      "change_pct": -1.7307162805333665
    },
    "GOOGL": {
      "price": 307.93,
      "change_pct": -0.9616621639006848
    },
    "AMZN": {
      "price": 209.8,
      "change_pct": -2.5092936802973873
    },
    "TSLA": {
      "price": 394.62,
      "change_pct": -1.1646254414306052
    },
    "META": {
      "price": 616.53,
      "change_pct": -0.9844859152667581
    },
    "BRK-B": {
      "price": 484.87,
      "change_pct": -1.5652279832717486
    },
    "BLK": {
      "price": 967.43,
      "change_pct": -0.3686882730352974
    }
  },
  "generated_at": 1773862325
}